mangoes-3.1.0.dist-info/RECORD
mangoes-3.1.0.dist-info/LICENSE
mangoes-3.1.0.dist-info/WHEEL
mangoes-3.1.0.dist-info/top_level.txt
mangoes-3.1.0.dist-info/METADATA
mangoes/dataset.py
mangoes/evaluate.py
mangoes/constants.py
mangoes/weighting.py
mangoes/vocabulary.py
mangoes/__init__.py
mangoes/visualize.py
mangoes/composition.py
mangoes/reduction.py
mangoes/context.py
mangoes/base.py
mangoes/corpus.py
mangoes/counting.py
mangoes/modeling/training_utils.py
mangoes/modeling/tokenizer.py
mangoes/modeling/bert_finetuning.py
mangoes/modeling/coref.py
mangoes/modeling/finetuning.py
mangoes/modeling/__init__.py
mangoes/modeling/bert_pretraining.py
mangoes/modeling/transformer_base.py
mangoes/modeling/bert_base.py
mangoes/modeling/enhanced_models/ernie.py
mangoes/modeling/enhanced_models/hck_transformer.py
mangoes/modeling/enhanced_models/__init__.py
mangoes/modeling/enhanced_models/kepler.py
mangoes/modeling/enhanced_models/kadapter.py
mangoes/modeling/enhanced_models/libert.py
mangoes/evaluation/statistics.py
mangoes/evaluation/__init__.py
mangoes/evaluation/outlier.py
mangoes/evaluation/base.py
mangoes/evaluation/similarity.py
mangoes/evaluation/analogy.py
mangoes/resources/fr/similarity/rg65-fr.txt
mangoes/resources/en/outlier_detection/wiki-sem-500-tokenized.zip
mangoes/resources/en/outlier_detection/8-8-8/Information_Technology_companies.txt
mangoes/resources/en/outlier_detection/8-8-8/Apostles_of_Jesus_Christ.txt
mangoes/resources/en/outlier_detection/8-8-8/European_football_teams.txt
mangoes/resources/en/outlier_detection/8-8-8/Big_cats.txt
mangoes/resources/en/outlier_detection/8-8-8/Solar_System_planets.txt
mangoes/resources/en/outlier_detection/8-8-8/German_car_manufacturers.txt
mangoes/resources/en/outlier_detection/8-8-8/SouthAmerica.txt
mangoes/resources/en/outlier_detection/8-8-8/Months.txt
mangoes/resources/en/similarity/men.txt
mangoes/resources/en/similarity/rareword.txt
mangoes/resources/en/similarity/wordsim353.txt
mangoes/resources/en/similarity/rg65.txt
mangoes/resources/en/similarity/ws353_relatedness.txt
mangoes/resources/en/similarity/mturk.txt
